pywkcloud/__init__.py
pywkcloud/storage/__init__.py
pywkcloud/storage/kodo_utils.py
pywkcloud/storage/oss_utils.py
pywkcloud/storage/storage_base.py
Pywkcloud-1.0.3.dist-info/METADATA
Pywkcloud-1.0.3.dist-info/WHEEL
Pywkcloud-1.0.3.dist-info/top_level.txt
Pywkcloud-1.0.3.dist-info/RECORD
