Metadata-Version: 2.1
Name: Pywkcloud
Version: 1.0.3
Summary: wangkai python cloud tools
Home-page: https://gitee.com/lovelong1/pywktools
Author: wangkai
Author-email: 1719456@qq.com
License: MIT License
Keywords: wangkai python cloud tools
Platform: any
Requires-Dist: pywkmisc
